sparglim/__init__.py
sparglim/exceptions.py
sparglim/log.py
sparglim/py.typed
sparglim/utils.py
sparglim/config/__init__.py
sparglim/config/builder.py
sparglim/config/configer.py
sparglim/config/k8s.py
sparglim/server/__init__.py
sparglim/server/cli.py
sparglim/server/daemon.py
sparglim/server/tailer.py
sparglim/sql/__init__.py
sparglim/sql/magic.py
sparglim-0.2.1.dist-info/METADATA
sparglim-0.2.1.dist-info/WHEEL
sparglim-0.2.1.dist-info/entry_points.txt
sparglim-0.2.1.dist-info/licenses/LICENSE
sparglim-0.2.1.dist-info/RECORD
