Metadata-Version: 2.1
Name: sparglim
Version: 0.2.1
Summary: sparglim
Project-URL: Source, https://github.com/wh1isper/sparglim
Author-email: wh1isper <9573586@qq.com>
License: BSD license
License-File: LICENSE
Keywords: ipython,magic,pyspark,sparglim,spark
Classifier: Programming Language :: Python :: 3
Classifier: Programming Language :: Python :: 3.8
Classifier: Programming Language :: Python :: 3.9
Classifier: Programming Language :: Python :: 3.10
Classifier: Programming Language :: Python :: 3.11
Requires-Python: >=3.8
Requires-Dist: click
Requires-Dist: findspark
Requires-Dist: kubernetes
Requires-Dist: loguru
Requires-Dist: psutil
Provides-Extra: all
Requires-Dist: sparglim[magic]; extra == 'all'
Requires-Dist: sparglim[pyspark]; extra == 'all'
Provides-Extra: dev
Requires-Dist: sparglim[test]; extra == 'dev'
Provides-Extra: magic
Requires-Dist: ipython; extra == 'magic'
Requires-Dist: sparglim[pyspark]; extra == 'magic'
Provides-Extra: pyspark
Requires-Dist: pyspark[connect,pandas-on-spark,sql]; extra == 'pyspark'
Provides-Extra: test
Requires-Dist: pytest; extra == 'test'
Requires-Dist: pytest-cov; extra == 'test'
Requires-Dist: pytest-timeout; extra == 'test'
Requires-Dist: pytype; extra == 'test'
Requires-Dist: sparglim[all]; extra == 'test'
